setup.py
distributions_cardos/Binomialdistribution.py
distributions_cardos/Gaussiandistribution.py
distributions_cardos/Generaldistribution.py
distributions_cardos/__init__.py
distributions_cardos.egg-info/PKG-INFO
distributions_cardos.egg-info/SOURCES.txt
distributions_cardos.egg-info/dependency_links.txt
distributions_cardos.egg-info/not-zip-safe
distributions_cardos.egg-info/top_level.txt